mauribooks/__init__.py
mauribooks/book_client.py
mauribooks/book_config.py
mauribooks/schemas/__init__.py
mauribooks/schemas/schema.py
mauribooks-1.0.0.dist-info/METADATA
mauribooks-1.0.0.dist-info/WHEEL
mauribooks-1.0.0.dist-info/top_level.txt
mauribooks-1.0.0.dist-info/RECORD
