Metadata-Version: 2.4
Name: mauribooks
Version: 1.0.0
Summary: SDK Python pour accéder à l’API MauriBooks
Author-email: Daouda Ba <daoudaba4500@gmail.com>
Classifier: Development Status :: 3 - Alpha
Classifier: Programming Language :: Python :: 3
Classifier: License :: OSI Approved :: MIT License
Classifier: Operating System :: OS Independent
Requires-Python: >=3.11
Requires-Dist: httpx>=0.28.1
Requires-Dist: pydantic>=2.11.3
Requires-Dist: backoff>=2.2.1
Requires-Dist: numpy>=2.2.4
Requires-Dist: pandas>=2.2.3
Requires-Dist: python-dotenv
Requires-Dist: gdown
